SMS_BP/__init__.py
SMS_BP/condensate_movement.py
SMS_BP/config_schema.py
SMS_BP/errors.py
SMS_BP/json_validator_converter.py
SMS_BP/probability_functions.py
SMS_BP/run_cell_simulation.py
SMS_BP/sim_config.json
SMS_BP/sim_config.md
SMS_BP/simulate_cell.py
SMS_BP/simulate_foci.py
SMS_BP/cells/__init__.py
SMS_BP/cells/budding_yeast_cell.py
SMS_BP/cells/cell_factory.py
SMS_BP/utils/__init__.py
SMS_BP/utils/decorators.py
SMS_BP/utils/maskMaker.py
sms_bp-1.0.1.dist-info/METADATA
sms_bp-1.0.1.dist-info/WHEEL
sms_bp-1.0.1.dist-info/entry_points.txt
sms_bp-1.0.1.dist-info/RECORD
