Metadata-Version: 2.4
Name: SMS_BP
Version: 1.0.1
Summary: Single Molecule Simulations and Microscopy Simulations developed for the Weber Lab by Baljyot Singh Parmar
Project-URL: Documentation, https://joemans3.github.io/SMS_BP/
Project-URL: Source code, https://github.com/joemans3/SMS_BP
Author-email: Baljyot Singh Parmar <baljyotparmar@hotmail.com>
Maintainer-email: Baljyot Singh Parmar <baljyotparmar@hotmail.com>
License: ---
Keywords: SMS
Requires-Python: >=3.12
Requires-Dist: boundedfbm>=0.4.0
Requires-Dist: jsonschema>=4.23.0
Requires-Dist: numpy>=1.21.2
Requires-Dist: pydantic>=2.9.2
Requires-Dist: scikit-image>=0.18.3
Requires-Dist: scipy>=1.7.1
Requires-Dist: typer>=0.12.5
